{"cameraMode":{"drawMode":0,"name":"Shaded","section":"Shading Mode"},"sceneLighting":false,"audioPlay":false,"sceneViewState":{"m_AlwaysRefresh":false,"showFog":true,"showSkybox":false,"showFlares":true,"showImageEffects":true,"showParticleSystems":true,"showVisualEffectGraphs":true,"m_FxEnabled":true},"in2DMode":false,"pivot":{"x":509.5,"y":162.0,"z":0.0},"rotation":{"x":0.39801663160324099,"y":-0.098774753510952,"z":0.04315367713570595,"w":0.9110225439071655},"size":534.6347045898438,"orthographic":false}